LICENSE.txt
MANIFEST.in
README.md
setup.py
jk_svg/AbstractSVGElement.py
jk_svg/BoundingBox.py
jk_svg/PointsList.py
jk_svg/SVGCircle.py
jk_svg/SVGDefs.py
jk_svg/SVGEllipse.py
jk_svg/SVGGenericElement.py
jk_svg/SVGGraphic.py
jk_svg/SVGGroup.py
jk_svg/SVGLine.py
jk_svg/SVGMask.py
jk_svg/SVGPath.py
jk_svg/SVGPolygon.py
jk_svg/SVGPolyline.py
jk_svg/SVGRect.py
jk_svg/SVGText.py
jk_svg/Transformer.py
jk_svg/UnitValue.py
jk_svg/_AttrMixinCXCY.py
jk_svg/_AttrMixinClass.py
jk_svg/_AttrMixinMaskContentUnits.py
jk_svg/_AttrMixinPoints.py
jk_svg/_AttrMixinR.py
jk_svg/_AttrMixinRXRY.py
jk_svg/_AttrMixinStyle.py
jk_svg/_AttrMixinTextContent.py
jk_svg/_AttrMixinWidthHeight.py
jk_svg/_AttrMixinX1Y1X2Y2.py
jk_svg/_AttrMixinXY.py
jk_svg/_GroupElementsMixin.py
jk_svg/__init__.py
jk_svg.egg-info/PKG-INFO
jk_svg.egg-info/SOURCES.txt
jk_svg.egg-info/dependency_links.txt
jk_svg.egg-info/not-zip-safe
jk_svg.egg-info/top_level.txt