Metadata-Version: 2.1
Name: jk-svg
Version: 0.2021.1.2
Summary: This Python module implements a set of classes for easy, programmatic generation of SVG graphics.
Home-page: UNKNOWN
Author: Jürgen Knauth
Author-email: pubsrc@binary-overflow.de
License: Apache2
Keywords: svg
Platform: UNKNOWN
Classifier: Development Status :: 4 - Beta
Classifier: License :: OSI Approved :: Apache Software License
Classifier: Programming Language :: Python :: 3
